MANIFEST.in
README
requirements.txt
setup.py
ajenti.plugin.packages.egg-info/PKG-INFO
ajenti.plugin.packages.egg-info/SOURCES.txt
ajenti.plugin.packages.egg-info/dependency_links.txt
ajenti.plugin.packages.egg-info/requires.txt
ajenti.plugin.packages.egg-info/top_level.txt
ajenti_plugin_packages/README.md
ajenti_plugin_packages/__init__.py
ajenti_plugin_packages/api.py
ajenti_plugin_packages/bower.json
ajenti_plugin_packages/main.py
ajenti_plugin_packages/plugin.yml
ajenti_plugin_packages/requirements.txt
ajenti_plugin_packages/tasks.py
ajenti_plugin_packages/views.py
ajenti_plugin_packages/locale/app.pot
ajenti_plugin_packages/locale/af/LC_MESSAGES/app.js
ajenti_plugin_packages/locale/af/LC_MESSAGES/app.po
ajenti_plugin_packages/locale/af/LC_MESSAGES/app.po~
ajenti_plugin_packages/locale/ar/LC_MESSAGES/app.js
ajenti_plugin_packages/locale/ar/LC_MESSAGES/app.po
ajenti_plugin_packages/locale/ar/LC_MESSAGES/app.po~
ajenti_plugin_packages/locale/be/LC_MESSAGES/app.js
ajenti_plugin_packages/locale/be/LC_MESSAGES/app.po
ajenti_plugin_packages/locale/be/LC_MESSAGES/app.po~
ajenti_plugin_packages/locale/bg/LC_MESSAGES/app.js
ajenti_plugin_packages/locale/bg/LC_MESSAGES/app.po
ajenti_plugin_packages/locale/bg/LC_MESSAGES/app.po~
ajenti_plugin_packages/locale/bn/LC_MESSAGES/app.js
ajenti_plugin_packages/locale/bn/LC_MESSAGES/app.po
ajenti_plugin_packages/locale/bn/LC_MESSAGES/app.po~
ajenti_plugin_packages/locale/bs/LC_MESSAGES/app.js
ajenti_plugin_packages/locale/bs/LC_MESSAGES/app.po
ajenti_plugin_packages/locale/ca/LC_MESSAGES/app.js
ajenti_plugin_packages/locale/ca/LC_MESSAGES/app.po
ajenti_plugin_packages/locale/ca/LC_MESSAGES/app.po~
ajenti_plugin_packages/locale/cs/LC_MESSAGES/app.js
ajenti_plugin_packages/locale/cs/LC_MESSAGES/app.po
ajenti_plugin_packages/locale/cs/LC_MESSAGES/app.po~
ajenti_plugin_packages/locale/da/LC_MESSAGES/app.js
ajenti_plugin_packages/locale/da/LC_MESSAGES/app.po
ajenti_plugin_packages/locale/da/LC_MESSAGES/app.po~
ajenti_plugin_packages/locale/de/LC_MESSAGES/app.js
ajenti_plugin_packages/locale/de/LC_MESSAGES/app.po
ajenti_plugin_packages/locale/de/LC_MESSAGES/app.po~
ajenti_plugin_packages/locale/el/LC_MESSAGES/app.js
