Metadata-Version: 1.2
Name: ajenti.plugin.packages
Version: 0.36
Summary: Packages
Home-page: https://ajenti.org
Author: Ajenti project
Author-email: e@ajenti.org
License: UNKNOWN
Platform: UNKNOWN
Requires-Python: >=3
